wordgeek/__init__.py
wordgeek/wk.py
wordgeek-0.0.4.dist-info/LICENSE
wordgeek-0.0.4.dist-info/METADATA
wordgeek-0.0.4.dist-info/WHEEL
wordgeek-0.0.4.dist-info/top_level.txt
wordgeek-0.0.4.dist-info/RECORD
