Metadata-Version: 2.1
Name: wordgeek
Version: 0.0.4
Summary: windows命令行查词
Home-page: https://github.com/Bsheepcoder/wordgeek
Author: Husile
Author-email: 18947336207@163.com
Classifier: Programming Language :: Python :: 3
Classifier: License :: OSI Approved :: Apache Software License
Classifier: Operating System :: OS Independent
License-File: LICENSE
